{
   "IsSuccessful":true,
   "Message":null,
   "Response":[
      {
         "Id":1,
         "Title":"ซ่อมรถ",
         "Description":null,
         "CategoryId":0,
         "IsActive":true,
         "CreatedDate":"\/Date(1616147741933)\/",
         "ModifiedDate":"\/Date(1616214114900)\/",
         "CreatedBy":1,
         "ModifiedBy":1
      },
      {
         "Id":3,
         "Title":"แมว",
         "Description":null,
         "CategoryId":0,
         "IsActive":true,
         "CreatedDate":"\/Date(1616148311900)\/",
         "ModifiedDate":"\/Date(1616148311900)\/",
         "CreatedBy":1,
         "ModifiedBy":1
      },
      {
         "Id":4,
         "Title":null,
         "Description":null,
         "CategoryId":0,
         "IsActive":true,
         "CreatedDate":"\/Date(1616213075893)\/",
         "ModifiedDate":"\/Date(1616213075893)\/",
         "CreatedBy":1,
         "ModifiedBy":1
      },
      {
         "Id":5,
         "Title":"แมว",
         "Description":null,
         "CategoryId":0,
         "IsActive":true,
         "CreatedDate":"\/Date(1616213078833)\/",
         "ModifiedDate":"\/Date(1616213078833)\/",
         "CreatedBy":1,
         "ModifiedBy":1
      },
      {
         "Id":6,
         "Title":"อาหารแมว",
         "Description":null,
         "CategoryId":0,
         "IsActive":true,
         "CreatedDate":"\/Date(1616214079210)\/",
         "ModifiedDate":"\/Date(1616214079210)\/",
         "CreatedBy":1,
         "ModifiedBy":1
      }
   ]
}
